[
    {
        "score": 0,
        "level": 0,
        "win": false,
        "timestamp": "06/14/2024 13:49"
    },
    {
        "score": 15000,
        "level": 3,
        "win": false,
        "timestamp": "06/14/2024 14:48"
    },
    {
        "score": 400,
        "level": 0,
        "win": false,
        "timestamp": "06/14/2024 14:49"
    },
    {
        "score": 2500,
        "level": 1,
        "win": false,
        "timestamp": "06/14/2024 14:49"
    },
    {
        "score": 7200,
        "level": 2,
        "win": false,
        "timestamp": "06/14/2024 14:49"
    },
    {
        "score": 35800,
        "level": 4,
        "win": false,
        "timestamp": "06/14/2024 14:50"
    },
    {
        "score": 0,
        "level": 0,
        "win": false,
        "timestamp": "06/14/2024 14:52"
    },
    {
        "score": 0,
        "level": 0,
        "win": false,
        "timestamp": "06/14/2024 14:54"
    },
    {
        "score": 0,
        "level": 0,
        "win": false,
        "timestamp": "06/14/2024 14:57"
    }
]